PyBinglate/__init__.py
PyBinglate/client.py
PyBinglate/utils.py
PyBinglate-0.2.71.dist-info/LICENSE
PyBinglate-0.2.71.dist-info/METADATA
PyBinglate-0.2.71.dist-info/WHEEL
PyBinglate-0.2.71.dist-info/top_level.txt
PyBinglate-0.2.71.dist-info/RECORD
