Metadata-Version: 2.1
Name: PyBinglate
Version: 0.2.71
Summary: Bing translator client for python
Home-page: https://github.com/Wirtos/PyBinglate
Author: Wirtos_new
Author-email: Wirtos.new@gmail.com
License: UNKNOWN
Project-URL: Source Code, https://github.com/Wirtos/PyBinglate
Keywords: bing translator translation microsoft
Platform: UNKNOWN
Classifier: Programming Language :: Python :: 3
Classifier: License :: OSI Approved :: MIT License
Classifier: Operating System :: OS Independent
Requires-Dist: requests
